{
  "$schema": "http://cyclonedx.org/schema/bom-1.4.schema.json",
  "bomFormat": "CycloneDX",
  "specVersion": "1.4",
  "serialNumber": "urn:uuid:d9c4a96b-6299-43f5-9d34-05b6b65b3224",
  "version": 1,
  "metadata": {
    "timestamp": "2023-11-15T21:51:07.298192+00:00",
    "tools": [
      {
        "vendor": "CycloneDX",
        "name": "cyclonedx-python-lib",
        "version": "3.1.5",
        "externalReferences": [
          {
            "url": "https://github.com/CycloneDX/cyclonedx-python-lib/actions",
            "type": "build-system"
          },
          {
            "url": "https://pypi.org/project/cyclonedx-python-lib/",
            "type": "distribution"
          },
          {
            "url": "https://cyclonedx.github.io/cyclonedx-python-lib/",
            "type": "documentation"
          },
          {
            "url": "https://github.com/CycloneDX/cyclonedx-python-lib/issues",
            "type": "issue-tracker"
          },
          {
            "url": "https://github.com/CycloneDX/cyclonedx-python-lib/blob/main/LICENSE",
            "type": "license"
          },
          {
            "url": "https://github.com/CycloneDX/cyclonedx-python-lib/blob/main/CHANGELOG.md",
            "type": "release-notes"
          },
          {
            "url": "https://github.com/CycloneDX/cyclonedx-python-lib",
            "type": "vcs"
          },
          {
            "url": "https://cyclonedx.org",
            "type": "website"
          }
        ]
      }
    ],
    "component": {
      "type": "application",
      "bom-ref": "cc59825a-ecb6-4f62-be80-4978b0a97c86",
      "name": "NewJuliaProject",
      "version": "0.1.0"
    }
  },
  "components": [
    {
      "type": "library",
      "bom-ref": "fcddce08-cbcf-43e1-9fe1-c50b99352fc8",
      "name": "AbstractFFTs",
      "version": "0.5.0"
    },
    {
      "type": "library",
      "bom-ref": "a2b7d745-63b7-40dc-96be-75ec153c5686",
      "name": "AbstractTrees",
      "version": "0.3.4"
    },
    {
      "type": "library",
      "bom-ref": "67c12066-d98c-4a4b-bf76-7f644a086846",
      "name": "Adapt",
      "version": "2.4.0"
    },
    {
      "type": "library",
      "bom-ref": "57d805eb-bfd8-42b5-83f1-d43a77f775a4",
      "name": "ArrayLayouts",
      "version": "0.4.12"
    },
    {
      "type": "library",
      "bom-ref": "2248a1a0-11a4-42b7-9252-2e0fc4df1bb6",
      "name": "Artifacts",
      "version": "1.3.0"
    },
    {
      "type": "library",
      "bom-ref": "8d106c0a-139f-4784-b8a2-3da9618846a6",
      "name": "Base64"
    },
    {
      "type": "library",
      "bom-ref": "d130e23c-4d48-48ca-8e03-1455ca34dcf9",
      "name": "BinaryProvider",
      "version": "0.5.10"
    },
    {
      "type": "library",
      "bom-ref": "c0f970d9-3d10-41f5-a84c-ab0d71e8190c",
      "name": "CEnum",
      "version": "0.4.2"
    },
    {
      "type": "library",
      "bom-ref": "3eac72bc-ed27-4850-a14c-6159c2bd3b8e",
      "name": "CUDA",
      "version": "1.3.3"
    },
    {
      "type": "library",
      "bom-ref": "5a45c1af-e757-4b56-8cf3-50b8987185db",
      "name": "ChainRules",
      "version": "0.7.70"
    },
    {
      "type": "library",
      "bom-ref": "2ca0992e-28f9-4d8e-884d-b486d96ea61b",
      "name": "ChainRulesCore",
      "version": "0.9.45"
    },
    {
      "type": "library",
      "bom-ref": "22e560c5-73c4-41bd-9fed-e7512d64f4d9",
      "name": "CodecZlib",
      "version": "0.7.3"
    },
    {
      "type": "library",
      "bom-ref": "9c5bb252-2eef-4da6-b26f-ae9d49d25049",
      "name": "ColorSchemes",
      "version": "3.24.0"
    },
    {
      "type": "library",
      "bom-ref": "49bcee9d-c698-47b0-9dcc-fc7411d0c573",
      "name": "ColorTypes",
      "version": "0.11.4"
    },
    {
      "type": "library",
      "bom-ref": "e1aa2158-d760-4495-8612-02c3fb2b4f19",
      "name": "ColorVectorSpace",
      "version": "0.9.10"
    },
    {
      "type": "library",
      "bom-ref": "5cdf9554-0e10-45a6-b5d6-4a501e81b734",
      "name": "Colors",
      "version": "0.12.10"
    },
    {
      "type": "library",
      "bom-ref": "90df3e56-0cf3-4f9b-a5e1-7f9dd6c94060",
      "name": "CommonSubexpressions",
      "version": "0.3.0"
    },
    {
      "type": "library",
      "bom-ref": "3d4c9f52-345b-403c-b234-65f204846a11",
      "name": "Compat",
      "version": "3.46.2"
    },
    {
      "type": "library",
      "bom-ref": "1efa25fc-86dd-45be-88ae-5beb11f4b75d",
      "name": "CompilerSupportLibraries_jll",
      "version": "0.3.4+0"
    },
    {
      "type": "library",
      "bom-ref": "97da55b6-246c-4bc8-9953-d8172a55f57e",
      "name": "Contour",
      "version": "0.5.7"
    },
    {
      "type": "library",
      "bom-ref": "5c1f18cd-853b-45ab-b32e-15de4b0c91cd",
      "name": "CpuId",
      "version": "0.2.2"
    },
    {
      "type": "library",
      "bom-ref": "8859c1d4-bd04-4421-aa4b-f10b8090e1a5",
      "name": "DataAPI",
      "version": "1.15.0"
    },
    {
      "type": "library",
      "bom-ref": "35b45f27-8334-4601-8c0c-18ceb124b191",
      "name": "DataStructures",
      "version": "0.18.15"
    },
    {
      "type": "library",
      "bom-ref": "15e38da5-757b-4fd6-b011-752a76b616e6",
      "name": "DataValueInterfaces",
      "version": "1.0.0"
    },
    {
      "type": "library",
      "bom-ref": "cb7a74b3-9b7c-42b8-9794-cf9e274d07ec",
      "name": "Dates"
    },
    {
      "type": "library",
      "bom-ref": "3bea8baf-b79f-4a9e-b02d-e5fdab80dd6a",
      "name": "DelimitedFiles"
    },
    {
      "type": "library",
      "bom-ref": "5a8351b8-d6c4-43a3-b759-66dcba61527f",
      "name": "DiffResults",
      "version": "1.0.3"
    },
    {
      "type": "library",
      "bom-ref": "69fc3192-0d4d-41c2-8b4e-cf198c715cb3",
      "name": "DiffRules",
      "version": "1.5.0"
    },
    {
      "type": "library",
      "bom-ref": "9f6f6eec-ef1b-4867-967e-300b268020e2",
      "name": "Distributed"
    },
    {
      "type": "library",
      "bom-ref": "b95cd71a-4049-4396-89f6-d87af4487485",
      "name": "DocStringExtensions",
      "version": "0.8.6"
    },
    {
      "type": "library",
      "bom-ref": "b9eed526-41d7-4ad7-ad33-c827536b108e",
      "name": "EarCut_jll",
      "version": "2.1.5+1"
    },
    {
      "type": "library",
      "bom-ref": "f79520a5-c483-4d26-a7bb-b2ff984f2f51",
      "name": "ExprTools",
      "version": "0.1.10"
    },
    {
      "type": "library",
      "bom-ref": "7d07c276-3c3d-467c-ac2b-25138fa916d1",
      "name": "FFMPEG",
      "version": "0.2.4"
    },
    {
      "type": "library",
      "bom-ref": "7e681fe8-54da-4e21-bd93-f52da776af43",
      "name": "FillArrays",
      "version": "0.10.2"
    },
    {
      "type": "library",
      "bom-ref": "33fc5337-06be-4863-9e8d-d70c50cb8c1b",
      "name": "FixedPointNumbers",
      "version": "0.8.4"
    },
    {
      "type": "library",
      "bom-ref": "69849c29-b6aa-44bd-a818-2d1867776990",
      "name": "Flux",
      "version": "0.11.1"
    },
    {
      "type": "library",
      "bom-ref": "a6af0782-2a7e-41c0-a258-b6752c17f5e4",
      "name": "Formatting",
      "version": "0.4.2"
    },
    {
      "type": "library",
      "bom-ref": "843c4829-20c3-41ca-9805-7fa2cb9fee4f",
      "name": "ForwardDiff",
      "version": "0.10.36"
    },
    {
      "type": "library",
      "bom-ref": "0a59cbf8-3905-43b0-97f6-04b4e1bb11d3",
      "name": "Functors",
      "version": "0.1.0"
    },
    {
      "type": "library",
      "bom-ref": "27805aaa-7435-40d0-ac91-135394cc1bc9",
      "name": "GPUArrays",
      "version": "5.2.1"
    },
    {
      "type": "library",
      "bom-ref": "c72c560d-8cc7-472c-a70a-ea026789e64d",
      "name": "GPUCompiler",
      "version": "0.6.1"
    },
    {
      "type": "library",
      "bom-ref": "cbbae94a-6dbe-4210-b580-515f9dd6bbd0",
      "name": "GR",
      "version": "0.52.0"
    },
    {
      "type": "library",
      "bom-ref": "6417c992-cc9c-4eb8-8d6a-c7c2fc3b1822",
      "name": "GeometryBasics",
      "version": "0.3.13"
    },
    {
      "type": "library",
      "bom-ref": "51bc5a0b-2f17-4072-a838-f2d4cd4152bd",
      "name": "GeometryTypes",
      "version": "0.8.5"
    },
    {
      "type": "library",
      "bom-ref": "46e10ea9-56bf-47de-8487-9ee915d3b2da",
      "name": "Grisu",
      "version": "1.0.2"
    },
    {
      "type": "library",
      "bom-ref": "ecd84623-e670-47be-aed5-ca0db78e6b5d",
      "name": "HTTP",
      "version": "0.8.19"
    },
    {
      "type": "library",
      "bom-ref": "eb4ed38f-bf3b-4347-8b17-f6ee22c9c9e0",
      "name": "IRTools",
      "version": "0.4.11"
    },
    {
      "type": "library",
      "bom-ref": "eba4d987-8ccf-432d-8321-74c39cdb0486",
      "name": "IniFile",
      "version": "0.5.1"
    },
    {
      "type": "library",
      "bom-ref": "0d94b8d4-0b80-40d9-9f20-08d39304ad34",
      "name": "InteractiveUtils"
    },
    {
      "type": "library",
      "bom-ref": "d0b3e7e8-f4be-49c6-8050-33610fbdb52e",
      "name": "IrrationalConstants",
      "version": "0.1.1"
    },
    {
      "type": "library",
      "bom-ref": "7f3a6c02-a669-4c1f-9943-ec4585234ca0",
      "name": "IterTools",
      "version": "1.4.0"
    },
    {
      "type": "library",
      "bom-ref": "c355c40c-ba0f-47a1-bd8d-7b8a808d5c8b",
      "name": "IteratorInterfaceExtensions",
      "version": "1.0.0"
    },
    {
      "type": "library",
      "bom-ref": "b160f85c-6d84-46e5-9576-5b5926b3552d",
      "name": "JLLWrappers",
      "version": "1.5.0"
    },
    {
      "type": "library",
      "bom-ref": "e86b2ead-f0a0-4640-be9d-866a3238fc4d",
      "name": "JSON",
      "version": "0.21.4"
    },
    {
      "type": "library",
      "bom-ref": "7cb0fe73-3d87-4786-a493-cce2c44c3883",
      "name": "Juno",
      "version": "0.8.4"
    },
    {
      "type": "library",
      "bom-ref": "5aad509e-360b-4a9a-8ceb-4daea239a166",
      "name": "LLVM",
      "version": "2.0.0"
    },
    {
      "type": "library",
      "bom-ref": "30149e62-0a3d-46af-b36e-b3b4a4edeb4a",
      "name": "LaTeXStrings",
      "version": "1.3.1"
    },
    {
      "type": "library",
      "bom-ref": "b18e1381-8dff-4b3c-b0aa-92cd399d1a7b",
      "name": "Latexify",
      "version": "0.14.12"
    },
    {
      "type": "library",
      "bom-ref": "6bf0079f-f67f-4a21-beec-899134c90635",
      "name": "LibGit2"
    },
    {
      "type": "library",
      "bom-ref": "09e8c931-e3cb-4d07-9f1a-e4c5718d12ed",
      "name": "Libdl"
    },
    {
      "type": "library",
      "bom-ref": "206edf9b-d52a-483c-85fc-f67f1d978bc2",
      "name": "LinearAlgebra"
    },
    {
      "type": "library",
      "bom-ref": "6c9d69c4-9220-428d-9570-efb8fa7647ac",
      "name": "LogExpFunctions",
      "version": "0.3.0"
    },
    {
      "type": "library",
      "bom-ref": "c538a269-1eb4-46f7-aaa1-840c931deca6",
      "name": "Logging"
    },
    {
      "type": "library",
      "bom-ref": "b1aa395d-d4d8-481b-96aa-097cc67cef29",
      "name": "LoopVectorization",
      "version": "0.8.26"
    },
    {
      "type": "library",
      "bom-ref": "0aa7692f-1df0-448c-a048-5e1dff462e3a",
      "name": "MacroTools",
      "version": "0.5.11"
    },
    {
      "type": "library",
      "bom-ref": "5d689dc6-c3be-41d4-a029-44f98cd7ed37",
      "name": "Markdown"
    },
    {
      "type": "library",
      "bom-ref": "bdfccd50-b3b4-4185-9acb-6af17a01a56d",
      "name": "MbedTLS",
      "version": "1.0.3"
    },
    {
      "type": "library",
      "bom-ref": "d9a64e14-f6da-4224-a22e-ed111edfa4db",
      "name": "MbedTLS_jll",
      "version": "2.16.8+1"
    },
    {
      "type": "library",
      "bom-ref": "7b538c71-2750-4bd9-9163-35ceb3ac6b7c",
      "name": "Measures",
      "version": "0.3.2"
    },
    {
      "type": "library",
      "bom-ref": "a2102126-177e-47f0-93b8-94ca317a7a0f",
      "name": "Media",
      "version": "0.5.0"
    },
    {
      "type": "library",
      "bom-ref": "603d48ac-cfff-4a80-8e44-ed11066e7a31",
      "name": "Missings",
      "version": "1.1.0"
    },
    {
      "type": "library",
      "bom-ref": "5a85e4f8-7ebd-480a-9015-d4512c1487b5",
      "name": "Mmap"
    },
    {
      "type": "library",
      "bom-ref": "9130c518-e1f8-49c5-84e0-ac920ea39293",
      "name": "NNlib",
      "version": "0.7.17"
    },
    {
      "type": "library",
      "bom-ref": "57255361-be78-4a84-80e1-55210848b54d",
      "name": "NaNMath",
      "version": "0.3.7"
    },
    {
      "type": "library",
      "bom-ref": "53d8c7b0-757f-492d-b2b6-9676943e4bbb",
      "name": "OffsetArrays",
      "version": "1.12.10"
    },
    {
      "type": "library",
      "bom-ref": "d6faae21-6011-4525-b1ae-8edddbea2a1f",
      "name": "OpenLibm_jll",
      "version": "0.7.1+0"
    },
    {
      "type": "library",
      "bom-ref": "c541b403-c8d8-4ac4-a2ff-9fa2a7399147",
      "name": "OpenSpecFun_jll",
      "version": "0.5.3+4"
    },
    {
      "type": "library",
      "bom-ref": "c2067f96-5afb-4c7e-95e6-84742a4ba700",
      "name": "OrderedCollections",
      "version": "1.5.0"
    },
    {
      "type": "library",
      "bom-ref": "43e4bbd6-181d-4804-8a8f-5ee5f76ae5da",
      "name": "Parsers",
      "version": "2.4.2"
    },
    {
      "type": "library",
      "bom-ref": "05762b2f-9e78-479c-99ad-531f338035c4",
      "name": "Pkg"
    },
    {
      "type": "library",
      "bom-ref": "73fd7995-fdd9-4cdb-b47c-133df3398613",
      "name": "PlotThemes",
      "version": "2.0.1"
    },
    {
      "type": "library",
      "bom-ref": "15fa6c74-48e3-4251-9cc0-ba7d9528b46d",
      "name": "PlotUtils",
      "version": "1.0.15"
    },
    {
      "type": "library",
      "bom-ref": "c748db08-7393-4291-b46b-d167269059cc",
      "name": "Plots",
      "version": "1.6.12"
    },
    {
      "type": "library",
      "bom-ref": "57353795-e1b7-47d8-942d-bdae67024b77",
      "name": "PrecompileTools",
      "version": "1.2.0"
    },
    {
      "type": "library",
      "bom-ref": "bfa8516c-e1c4-47dc-8ae2-f22a23fe5d2c",
      "name": "Preferences",
      "version": "1.4.1"
    },
    {
      "type": "library",
      "bom-ref": "46d1d2c5-0483-481a-9cf2-a1030d98a6e0",
      "name": "Printf"
    },
    {
      "type": "library",
      "bom-ref": "69d44174-3a01-4177-b92f-103dc9b8d785",
      "name": "Profile"
    },
    {
      "type": "library",
      "bom-ref": "18db3a4f-b260-46a3-816a-0d3ecc02f09b",
      "name": "REPL"
    },
    {
      "type": "library",
      "bom-ref": "89e0dd9f-1da6-4198-a849-6f5ba03e810d",
      "name": "Random"
    },
    {
      "type": "library",
      "bom-ref": "382e3093-bedf-44ec-84f8-85860ef788f7",
      "name": "RecipesBase",
      "version": "1.2.1"
    },
    {
      "type": "library",
      "bom-ref": "3a3b31c5-1f82-45d2-8cc2-dc76de7bd8f7",
      "name": "RecipesPipeline",
      "version": "0.1.13"
    },
    {
      "type": "library",
      "bom-ref": "f36c80e7-9191-4d7d-aef8-8bf1a4ad5ff9",
      "name": "Reexport",
      "version": "0.2.0"
    },
    {
      "type": "library",
      "bom-ref": "2502bd55-0e4b-4bde-8647-1f97c51ff96e",
      "name": "Requires",
      "version": "1.3.0"
    },
    {
      "type": "library",
      "bom-ref": "7e7bddad-8059-46e5-93fd-156c9e031455",
      "name": "SHA"
    },
    {
      "type": "library",
      "bom-ref": "ff3a36cf-92aa-4ef0-b8b6-4f3441dd27e5",
      "name": "SIMDPirates",
      "version": "0.8.26"
    },
    {
      "type": "library",
      "bom-ref": "ab7aed07-f862-4305-b209-985ae9849d7e",
      "name": "SLEEFPirates",
      "version": "0.5.5"
    },
    {
      "type": "library",
      "bom-ref": "2bf6aab8-dd2f-484f-9420-01a59fdf5313",
      "name": "Serialization"
    },
    {
      "type": "library",
      "bom-ref": "bc0f9bad-2bca-4260-a7fe-1568cb406461",
      "name": "SharedArrays"
    },
    {
      "type": "library",
      "bom-ref": "8507bb1a-991f-4e5a-af32-4965dab858e1",
      "name": "Showoff",
      "version": "0.3.2"
    },
    {
      "type": "library",
      "bom-ref": "d3666ce1-a74c-4367-9e8d-7d9aceeec95d",
      "name": "Sockets"
    },
    {
      "type": "library",
      "bom-ref": "f33269fa-ef8a-4a33-94f7-9e8ebe890e8e",
      "name": "SortingAlgorithms",
      "version": "1.2.0"
    },
    {
      "type": "library",
      "bom-ref": "0527015e-b003-4283-be90-0d18c2c66a05",
      "name": "SparseArrays"
    },
    {
      "type": "library",
      "bom-ref": "74c0c66a-5fc4-4ca3-8a7e-3d256ec8bad6",
      "name": "SpecialFunctions",
      "version": "1.8.3"
    },
    {
      "type": "library",
      "bom-ref": "89255495-3d11-45b4-96d5-49c88788b33d",
      "name": "StaticArrays",
      "version": "1.3.6"
    },
    {
      "type": "library",
      "bom-ref": "46666213-e593-4d18-b394-f7ca9f43e602",
      "name": "Statistics"
    },
    {
      "type": "library",
      "bom-ref": "214f4470-0000-4e1c-a993-96f3486e20aa",
      "name": "StatsAPI",
      "version": "1.7.0"
    },
    {
      "type": "library",
      "bom-ref": "ed10367b-21b7-4cde-afa5-7818622ecb55",
      "name": "StatsBase",
      "version": "0.33.21"
    },
    {
      "type": "library",
      "bom-ref": "9aa7db28-f956-43e5-b10c-ad39a3a944f5",
      "name": "StructArrays",
      "version": "0.6.11"
    },
    {
      "type": "library",
      "bom-ref": "b6f7626b-0822-40d0-ad8d-f8181796a8b8",
      "name": "TOML",
      "version": "1.0.3"
    },
    {
      "type": "library",
      "bom-ref": "b062ca52-3c38-4f68-ba35-8ad30215748b",
      "name": "TableTraits",
      "version": "1.0.1"
    },
    {
      "type": "library",
      "bom-ref": "fc51a3fc-27fa-4587-94ae-1de3f1897db7",
      "name": "Tables",
      "version": "1.11.1"
    },
    {
      "type": "library",
      "bom-ref": "91ffc197-ebeb-4891-96cf-ea6c17ba594b",
      "name": "TensorCore",
      "version": "0.1.1"
    },
    {
      "type": "library",
      "bom-ref": "e76baf49-8333-4027-8d95-d68f02b7468e",
      "name": "Test"
    },
    {
      "type": "library",
      "bom-ref": "077a3812-02cc-4137-a2f3-48bdff120d23",
      "name": "TimerOutputs",
      "version": "0.5.23"
    },
    {
      "type": "library",
      "bom-ref": "3e394188-2251-4c6b-813b-0a4561d00496",
      "name": "TranscodingStreams",
      "version": "0.9.13"
    },
    {
      "type": "library",
      "bom-ref": "5e557795-5362-4aa1-9741-57df08df6ded",
      "name": "UUIDs"
    },
    {
      "type": "library",
      "bom-ref": "ce111313-6fa1-410f-93d6-411fc7c40ead",
      "name": "UnPack",
      "version": "1.0.2"
    },
    {
      "type": "library",
      "bom-ref": "7ed97334-3175-4c7f-bcc1-2e68a947775a",
      "name": "Unicode"
    },
    {
      "type": "library",
      "bom-ref": "f7b68353-e8ee-4745-ac38-2de2ea77107b",
      "name": "VectorizationBase",
      "version": "0.12.33"
    },
    {
      "type": "library",
      "bom-ref": "180f43b3-de9b-465b-bace-1dec67a0154d",
      "name": "ZipFile",
      "version": "0.9.4"
    },
    {
      "type": "library",
      "bom-ref": "91fce14e-e86f-4246-a021-5670828b8f78",
      "name": "Zlib_jll",
      "version": "1.2.11+18"
    },
    {
      "type": "library",
      "bom-ref": "13337aba-3dbb-4aa6-9ef7-fd41700773b6",
      "name": "Zygote",
      "version": "0.5.17"
    },
    {
      "type": "library",
      "bom-ref": "c1b3e48d-ccfd-4077-bf4e-ad09226f0eaa",
      "name": "ZygoteRules",
      "version": "0.2.2"
    }
  ],
  "dependencies": [
    {
      "ref": "cc59825a-ecb6-4f62-be80-4978b0a97c86",
      "dependsOn": []
    },
    {
      "ref": "fcddce08-cbcf-43e1-9fe1-c50b99352fc8",
      "dependsOn": []
    },
    {
      "ref": "a2b7d745-63b7-40dc-96be-75ec153c5686",
      "dependsOn": []
    },
    {
      "ref": "67c12066-d98c-4a4b-bf76-7f644a086846",
      "dependsOn": []
    },
    {
      "ref": "57d805eb-bfd8-42b5-83f1-d43a77f775a4",
      "dependsOn": []
    },
    {
      "ref": "2248a1a0-11a4-42b7-9252-2e0fc4df1bb6",
      "dependsOn": []
    },
    {
      "ref": "8d106c0a-139f-4784-b8a2-3da9618846a6",
      "dependsOn": []
    },
    {
      "ref": "d130e23c-4d48-48ca-8e03-1455ca34dcf9",
      "dependsOn": []
    },
    {
      "ref": "c0f970d9-3d10-41f5-a84c-ab0d71e8190c",
      "dependsOn": []
    },
    {
      "ref": "3eac72bc-ed27-4850-a14c-6159c2bd3b8e",
      "dependsOn": []
    },
    {
      "ref": "5a45c1af-e757-4b56-8cf3-50b8987185db",
      "dependsOn": []
    },
    {
      "ref": "2ca0992e-28f9-4d8e-884d-b486d96ea61b",
      "dependsOn": []
    },
    {
      "ref": "22e560c5-73c4-41bd-9fed-e7512d64f4d9",
      "dependsOn": []
    },
    {
      "ref": "9c5bb252-2eef-4da6-b26f-ae9d49d25049",
      "dependsOn": []
    },
    {
      "ref": "49bcee9d-c698-47b0-9dcc-fc7411d0c573",
      "dependsOn": []
    },
    {
      "ref": "e1aa2158-d760-4495-8612-02c3fb2b4f19",
      "dependsOn": []
    },
    {
      "ref": "5cdf9554-0e10-45a6-b5d6-4a501e81b734",
      "dependsOn": []
    },
    {
      "ref": "90df3e56-0cf3-4f9b-a5e1-7f9dd6c94060",
      "dependsOn": []
    },
    {
      "ref": "3d4c9f52-345b-403c-b234-65f204846a11",
      "dependsOn": []
    },
    {
      "ref": "1efa25fc-86dd-45be-88ae-5beb11f4b75d",
      "dependsOn": []
    },
    {
      "ref": "97da55b6-246c-4bc8-9953-d8172a55f57e",
      "dependsOn": []
    },
    {
      "ref": "5c1f18cd-853b-45ab-b32e-15de4b0c91cd",
      "dependsOn": []
    },
    {
      "ref": "8859c1d4-bd04-4421-aa4b-f10b8090e1a5",
      "dependsOn": []
    },
    {
      "ref": "35b45f27-8334-4601-8c0c-18ceb124b191",
      "dependsOn": []
    },
    {
      "ref": "15e38da5-757b-4fd6-b011-752a76b616e6",
      "dependsOn": []
    },
    {
      "ref": "cb7a74b3-9b7c-42b8-9794-cf9e274d07ec",
      "dependsOn": []
    },
    {
      "ref": "3bea8baf-b79f-4a9e-b02d-e5fdab80dd6a",
      "dependsOn": []
    },
    {
      "ref": "5a8351b8-d6c4-43a3-b759-66dcba61527f",
      "dependsOn": []
    },
    {
      "ref": "69fc3192-0d4d-41c2-8b4e-cf198c715cb3",
      "dependsOn": []
    },
    {
      "ref": "9f6f6eec-ef1b-4867-967e-300b268020e2",
      "dependsOn": []
    },
    {
      "ref": "b95cd71a-4049-4396-89f6-d87af4487485",
      "dependsOn": []
    },
    {
      "ref": "b9eed526-41d7-4ad7-ad33-c827536b108e",
      "dependsOn": []
    },
    {
      "ref": "f79520a5-c483-4d26-a7bb-b2ff984f2f51",
      "dependsOn": []
    },
    {
      "ref": "7d07c276-3c3d-467c-ac2b-25138fa916d1",
      "dependsOn": []
    },
    {
      "ref": "7e681fe8-54da-4e21-bd93-f52da776af43",
      "dependsOn": []
    },
    {
      "ref": "33fc5337-06be-4863-9e8d-d70c50cb8c1b",
      "dependsOn": []
    },
    {
      "ref": "69849c29-b6aa-44bd-a818-2d1867776990",
      "dependsOn": []
    },
    {
      "ref": "a6af0782-2a7e-41c0-a258-b6752c17f5e4",
      "dependsOn": []
    },
    {
      "ref": "843c4829-20c3-41ca-9805-7fa2cb9fee4f",
      "dependsOn": []
    },
    {
      "ref": "0a59cbf8-3905-43b0-97f6-04b4e1bb11d3",
      "dependsOn": []
    },
    {
      "ref": "27805aaa-7435-40d0-ac91-135394cc1bc9",
      "dependsOn": []
    },
    {
      "ref": "c72c560d-8cc7-472c-a70a-ea026789e64d",
      "dependsOn": []
    },
    {
      "ref": "cbbae94a-6dbe-4210-b580-515f9dd6bbd0",
      "dependsOn": []
    },
    {
      "ref": "6417c992-cc9c-4eb8-8d6a-c7c2fc3b1822",
      "dependsOn": []
    },
    {
      "ref": "51bc5a0b-2f17-4072-a838-f2d4cd4152bd",
      "dependsOn": []
    },
    {
      "ref": "46e10ea9-56bf-47de-8487-9ee915d3b2da",
      "dependsOn": []
    },
    {
      "ref": "ecd84623-e670-47be-aed5-ca0db78e6b5d",
      "dependsOn": []
    },
    {
      "ref": "eb4ed38f-bf3b-4347-8b17-f6ee22c9c9e0",
      "dependsOn": []
    },
    {
      "ref": "eba4d987-8ccf-432d-8321-74c39cdb0486",
      "dependsOn": []
    },
    {
      "ref": "0d94b8d4-0b80-40d9-9f20-08d39304ad34",
      "dependsOn": []
    },
    {
      "ref": "d0b3e7e8-f4be-49c6-8050-33610fbdb52e",
      "dependsOn": []
    },
    {
      "ref": "7f3a6c02-a669-4c1f-9943-ec4585234ca0",
      "dependsOn": []
    },
    {
      "ref": "c355c40c-ba0f-47a1-bd8d-7b8a808d5c8b",
      "dependsOn": []
    },
    {
      "ref": "b160f85c-6d84-46e5-9576-5b5926b3552d",
      "dependsOn": []
    },
    {
      "ref": "e86b2ead-f0a0-4640-be9d-866a3238fc4d",
      "dependsOn": []
    },
    {
      "ref": "7cb0fe73-3d87-4786-a493-cce2c44c3883",
      "dependsOn": []
    },
    {
      "ref": "5aad509e-360b-4a9a-8ceb-4daea239a166",
      "dependsOn": []
    },
    {
      "ref": "30149e62-0a3d-46af-b36e-b3b4a4edeb4a",
      "dependsOn": []
    },
    {
      "ref": "b18e1381-8dff-4b3c-b0aa-92cd399d1a7b",
      "dependsOn": []
    },
    {
      "ref": "6bf0079f-f67f-4a21-beec-899134c90635",
      "dependsOn": []
    },
    {
      "ref": "09e8c931-e3cb-4d07-9f1a-e4c5718d12ed",
      "dependsOn": []
    },
    {
      "ref": "206edf9b-d52a-483c-85fc-f67f1d978bc2",
      "dependsOn": []
    },
    {
      "ref": "6c9d69c4-9220-428d-9570-efb8fa7647ac",
      "dependsOn": []
    },
    {
      "ref": "c538a269-1eb4-46f7-aaa1-840c931deca6",
      "dependsOn": []
    },
    {
      "ref": "b1aa395d-d4d8-481b-96aa-097cc67cef29",
      "dependsOn": []
    },
    {
      "ref": "0aa7692f-1df0-448c-a048-5e1dff462e3a",
      "dependsOn": []
    },
    {
      "ref": "5d689dc6-c3be-41d4-a029-44f98cd7ed37",
      "dependsOn": []
    },
    {
      "ref": "bdfccd50-b3b4-4185-9acb-6af17a01a56d",
      "dependsOn": []
    },
    {
      "ref": "d9a64e14-f6da-4224-a22e-ed111edfa4db",
      "dependsOn": []
    },
    {
      "ref": "7b538c71-2750-4bd9-9163-35ceb3ac6b7c",
      "dependsOn": []
    },
    {
      "ref": "a2102126-177e-47f0-93b8-94ca317a7a0f",
      "dependsOn": []
    },
    {
      "ref": "603d48ac-cfff-4a80-8e44-ed11066e7a31",
      "dependsOn": []
    },
    {
      "ref": "5a85e4f8-7ebd-480a-9015-d4512c1487b5",
      "dependsOn": []
    },
    {
      "ref": "9130c518-e1f8-49c5-84e0-ac920ea39293",
      "dependsOn": []
    },
    {
      "ref": "57255361-be78-4a84-80e1-55210848b54d",
      "dependsOn": []
    },
    {
      "ref": "53d8c7b0-757f-492d-b2b6-9676943e4bbb",
      "dependsOn": []
    },
    {
      "ref": "d6faae21-6011-4525-b1ae-8edddbea2a1f",
      "dependsOn": []
    },
    {
      "ref": "c541b403-c8d8-4ac4-a2ff-9fa2a7399147",
      "dependsOn": []
    },
    {
      "ref": "c2067f96-5afb-4c7e-95e6-84742a4ba700",
      "dependsOn": []
    },
    {
      "ref": "43e4bbd6-181d-4804-8a8f-5ee5f76ae5da",
      "dependsOn": []
    },
    {
      "ref": "05762b2f-9e78-479c-99ad-531f338035c4",
      "dependsOn": []
    },
    {
      "ref": "73fd7995-fdd9-4cdb-b47c-133df3398613",
      "dependsOn": []
    },
    {
      "ref": "15fa6c74-48e3-4251-9cc0-ba7d9528b46d",
      "dependsOn": []
    },
    {
      "ref": "c748db08-7393-4291-b46b-d167269059cc",
      "dependsOn": []
    },
    {
      "ref": "57353795-e1b7-47d8-942d-bdae67024b77",
      "dependsOn": []
    },
    {
      "ref": "bfa8516c-e1c4-47dc-8ae2-f22a23fe5d2c",
      "dependsOn": []
    },
    {
      "ref": "46d1d2c5-0483-481a-9cf2-a1030d98a6e0",
      "dependsOn": []
    },
    {
      "ref": "69d44174-3a01-4177-b92f-103dc9b8d785",
      "dependsOn": []
    },
    {
      "ref": "18db3a4f-b260-46a3-816a-0d3ecc02f09b",
      "dependsOn": []
    },
    {
      "ref": "89e0dd9f-1da6-4198-a849-6f5ba03e810d",
      "dependsOn": []
    },
    {
      "ref": "382e3093-bedf-44ec-84f8-85860ef788f7",
      "dependsOn": []
    },
    {
      "ref": "3a3b31c5-1f82-45d2-8cc2-dc76de7bd8f7",
      "dependsOn": []
    },
    {
      "ref": "f36c80e7-9191-4d7d-aef8-8bf1a4ad5ff9",
      "dependsOn": []
    },
    {
      "ref": "2502bd55-0e4b-4bde-8647-1f97c51ff96e",
      "dependsOn": []
    },
    {
      "ref": "7e7bddad-8059-46e5-93fd-156c9e031455",
      "dependsOn": []
    },
    {
      "ref": "ff3a36cf-92aa-4ef0-b8b6-4f3441dd27e5",
      "dependsOn": []
    },
    {
      "ref": "ab7aed07-f862-4305-b209-985ae9849d7e",
      "dependsOn": []
    },
    {
      "ref": "2bf6aab8-dd2f-484f-9420-01a59fdf5313",
      "dependsOn": []
    },
    {
      "ref": "bc0f9bad-2bca-4260-a7fe-1568cb406461",
      "dependsOn": []
    },
    {
      "ref": "8507bb1a-991f-4e5a-af32-4965dab858e1",
      "dependsOn": []
    },
    {
      "ref": "d3666ce1-a74c-4367-9e8d-7d9aceeec95d",
      "dependsOn": []
    },
    {
      "ref": "f33269fa-ef8a-4a33-94f7-9e8ebe890e8e",
      "dependsOn": []
    },
    {
      "ref": "0527015e-b003-4283-be90-0d18c2c66a05",
      "dependsOn": []
    },
    {
      "ref": "74c0c66a-5fc4-4ca3-8a7e-3d256ec8bad6",
      "dependsOn": []
    },
    {
      "ref": "89255495-3d11-45b4-96d5-49c88788b33d",
      "dependsOn": []
    },
    {
      "ref": "46666213-e593-4d18-b394-f7ca9f43e602",
      "dependsOn": []
    },
    {
      "ref": "214f4470-0000-4e1c-a993-96f3486e20aa",
      "dependsOn": []
    },
    {
      "ref": "ed10367b-21b7-4cde-afa5-7818622ecb55",
      "dependsOn": []
    },
    {
      "ref": "9aa7db28-f956-43e5-b10c-ad39a3a944f5",
      "dependsOn": []
    },
    {
      "ref": "b6f7626b-0822-40d0-ad8d-f8181796a8b8",
      "dependsOn": []
    },
    {
      "ref": "b062ca52-3c38-4f68-ba35-8ad30215748b",
      "dependsOn": []
    },
    {
      "ref": "fc51a3fc-27fa-4587-94ae-1de3f1897db7",
      "dependsOn": []
    },
    {
      "ref": "91ffc197-ebeb-4891-96cf-ea6c17ba594b",
      "dependsOn": []
    },
    {
      "ref": "e76baf49-8333-4027-8d95-d68f02b7468e",
      "dependsOn": []
    },
    {
      "ref": "077a3812-02cc-4137-a2f3-48bdff120d23",
      "dependsOn": []
    },
    {
      "ref": "3e394188-2251-4c6b-813b-0a4561d00496",
      "dependsOn": []
    },
    {
      "ref": "5e557795-5362-4aa1-9741-57df08df6ded",
      "dependsOn": []
    },
    {
      "ref": "ce111313-6fa1-410f-93d6-411fc7c40ead",
      "dependsOn": []
    },
    {
      "ref": "7ed97334-3175-4c7f-bcc1-2e68a947775a",
      "dependsOn": []
    },
    {
      "ref": "f7b68353-e8ee-4745-ac38-2de2ea77107b",
      "dependsOn": []
    },
    {
      "ref": "180f43b3-de9b-465b-bace-1dec67a0154d",
      "dependsOn": []
    },
    {
      "ref": "91fce14e-e86f-4246-a021-5670828b8f78",
      "dependsOn": []
    },
    {
      "ref": "13337aba-3dbb-4aa6-9ef7-fd41700773b6",
      "dependsOn": []
    },
    {
      "ref": "c1b3e48d-ccfd-4077-bf4e-ad09226f0eaa",
      "dependsOn": []
    }
  ]
}